trajectorize/__init__.py
trajectorize/_c_extension.pyd
trajectorize/_version.py
trajectorize/c_ext_utils/__init__.py
trajectorize/c_ext_utils/build_c_extension.py
trajectorize/c_ext_utils/process_sva_buffer.py
trajectorize/demos/__init__.py
trajectorize/demos/kerbin_duna_porkchop.py
trajectorize/demos/kerbin_duna_transfer.py
trajectorize/demos/kerbol_system.py
trajectorize/demos/kerbol_system_anim.py
trajectorize/demos/orbit.py
trajectorize/ephemeris/__init__.py
trajectorize/ephemeris/kerbol_system.py
trajectorize/ephemeris/kerbol_system_bodies.c
trajectorize/ephemeris/kerbol_system_ephemeris.c
trajectorize/ephemeris/state_vector.py
trajectorize/math_lib/__init__.py
trajectorize/math_lib/math_interfaces.py
trajectorize/math_lib/orbit_math.c
trajectorize/math_lib/rotations.c
trajectorize/math_lib/stumpuff_functions.c
trajectorize/orbit/__init__.py
trajectorize/orbit/conic_kepler.c
trajectorize/orbit/conic_kepler.py
trajectorize/orbit/universal_kepler.c
trajectorize/orbit/universal_kepler.py
trajectorize/tester_utils/__init__.py
trajectorize/tester_utils/fake_body.py
trajectorize/trajectory/__init__.py
trajectorize/trajectory/delta_v_estimate.c
trajectorize/trajectory/lambert.c
trajectorize/trajectory/transfer_orbit.c
trajectorize/trajectory/transfer_orbit.py
trajectorize/visualizers/__init__.py
trajectorize/visualizers/celestial_body_plot.py
trajectorize/visualizers/display_utils.py
trajectorize/visualizers/parula_colourmap.py
trajectorize/visualizers/planetary_transfer_plot.py
trajectorize/visualizers/porkchop_plot.py
trajectorize-0.0.8.dist-info/LICENSE
trajectorize-0.0.8.dist-info/METADATA
trajectorize-0.0.8.dist-info/WHEEL
trajectorize-0.0.8.dist-info/top_level.txt
trajectorize-0.0.8.dist-info/RECORD
