Metadata-Version: 2.1
Name: trajectorize
Version: 0.0.8
Summary: KSP Trajectory Optimization
Author-email: Mingde Yin <mdsuper@hotmail.com>
Maintainer-email: Mingde Yin <mdsuper@hotmail.com>
License: LGPLv3
Project-URL: homepage, https://github.com/itchono/trajectorize
Keywords: kerbal space program,trajectory,optimization
Classifier: Development Status :: 3 - Alpha
Classifier: Intended Audience :: Science/Research
Classifier: License :: OSI Approved :: GNU Lesser General Public License v3 (LGPLv3)
Classifier: Operating System :: OS Independent
Classifier: Programming Language :: C
Classifier: Programming Language :: Python :: 3
Classifier: Programming Language :: Python :: 3.8
Classifier: Programming Language :: Python :: 3.9
Classifier: Topic :: Scientific/Engineering
Classifier: Topic :: Scientific/Engineering :: Mathematics
Classifier: Topic :: Scientific/Engineering :: Physics
Classifier: Topic :: Scientific/Engineering :: Astronomy
Requires-Python: >=3.8
License-File: LICENSE
Requires-Dist: numpy (>=1.23.0)
Requires-Dist: matplotlib (>=3.4.0)
Requires-Dist: cffi (>=1.15.0)
